{
  "id": "nginx0003",
  "cmd": null,
  "cpus": 0.02,
  "mem": 10,
  "disk": 0,
  "instances": 5,
  "container": {
    "docker": {
      "image": "nginx:1.10",
      "network": "BRIDGE",
      "forcePullImage": false,
      "privileged": true,
      "parameters": [
        {
            "key": "label",
	    "value": "APP_ID=nginx"
        }
      ],
      "portMappings": [
        {
          "containerPort": 80,
          "protocol": "tcp",
          "name": "web"
        }
      ]
    },
    "type": "DOCKER",
    "volumes": [
      {
        "hostPath": "/home",
        "containerPath": "/data",
        "mode": "RW"
      }
    ]
  },
  "env": {
    "DB": "mysql"
  },
  "label": {
    "USER_ID": "1"
  },
  "killPolicy": {
    "duration": 5
  },
  "healthChecks": [
    {
      "protocol": "TCP",
      "path": "/",
      "portIndex": 0,
      "gracePeriodSeconds": 5,
      "intervalSeconds": 3,
      "timeoutSeconds": 3,
      "maxConsecutiveFailures": 3
    }
 ],
  "updatePolicy": {
	  "updateDelay": 10,
	  "maxRetries": 3
  }
}
